{
  "title": "¿Qué niño es este?",
  "number": "91",
  "verses": "3",
  "sections": {
    "1": {
      "verse": "1",
      "text": [
        "¿Qué niño es este",
        "que yace en el regazo de María?"
      ]
    },
    "2": {
      "verse": "1",
      "text": [
        "¿A quien los ángeles cantan"
      ]
    },
    "3": {
      "verse": "1",
      "text": [
        "mientras en vela están los pastores?"
      ]
    },
    "4": {
      "verse": "coro",
      "text": [
        "El es Jesús, el Rey,",
        "a quien cantaron los ángeles."
      ]
    },
    "5": {
      "verse": "coro",
      "text": [
        "Dad, dad alabanza y honra al niño de María."
      ]
    },
    "6": {
      "verse": "2",
      "text": [
        "¿Por qué en pesebre humilde está",
        "donde yacen bueyes y asnos?"
      ]
    },
    "7": {
      "verse": "2",
      "text": [
        "Es por amor que el Verbo"
      ]
    },
    "8": {
      "verse": "2",
      "text": [
        "se hizo hombre y vivió entre nosotros."
      ]
    },
    "9": {
      "verse": "coro",
      "text": [
        "El es Jesús, el Rey,",
        "a quien cantaron los ángeles."
      ]
    },
    "10": {
      "verse": "coro",
      "text": [
        "Dad, dad alabanza y honra al niño de María."
      ]
    },
    "11": {
      "verse": "3",
      "text": [
        "Traedle oro, incienso y mirra,",
        "y dadle ricos presentes."
      ]
    },
    "12": {
      "verse": "3",
      "text": [
        "El Rey de reyes la vida da;",
        "entronadle en los corazones."
      ]
    },
    "13": {
      "verse": "coro",
      "text": [
        "El es Jesús, el Rey,",
        "a quien cantaron los ángeles."
      ]
    },
    "14": {
      "verse": "coro",
      "text": [
        "Dad, dad alabanza y honra al niño de María."
      ]
    }
  }
}