{
  "title": "Mi mano ten",
  "number": "455",
  "sections": {
    "1": {
      "verse": "1",
      "text": [
        "Mi mano ten, Señor; me siento débil:"
      ]
    },
    "2": {
      "verse": "1",
      "text": [
        "sin ti no puedo riesgos afrontar;"
      ]
    },
    "3": {
      "verse": "1",
      "text": [
        "tenla Señor; mi vida el gozo llene"
      ]
    },
    "4": {
      "verse": "1",
      "text": [
        "de verme libre así de todo azar."
      ]
    },
    "5": {
      "verse": "2",
      "text": [
        "Mi mano ten; permite que me animen"
      ]
    },
    "6": {
      "verse": "2",
      "text": [
        "mi regocijo, mi esperanza en ti;"
      ]
    },
    "7": {
      "verse": "2",
      "text": [
        "tenla Señor, y compasivo impide"
      ]
    },
    "8": {
      "verse": "2",
      "text": [
        "que caiga en mal cual una vez caí."
      ]
    },
    "9": {
      "verse": "3",
      "text": [
        "Mi mano ten; mi senda es tenebrosa"
      ]
    },
    "10": {
      "verse": "3",
      "text": [
        "si no la alumbra tu radiante faz;"
      ]
    },
    "11": {
      "verse": "3",
      "text": [
        "por fe si alcanzo a percibir tu gloria,"
      ]
    },
    "12": {
      "verse": "3",
      "text": [
        "¡cuán grande gozo!, ¡cuán profunda paz!"
      ]
    }
  }
}